sip_logging/__init__.py
sip_logging/sip_logging.py
skasip_logging-1.0.14.dist-info/LICENSE.md
skasip_logging-1.0.14.dist-info/METADATA
skasip_logging-1.0.14.dist-info/WHEEL
skasip_logging-1.0.14.dist-info/top_level.txt
skasip_logging-1.0.14.dist-info/RECORD
