Metadata-Version: 2.1
Name: skasip-logging
Version: 1.0.14
Summary: SIP logging module.
Home-page: https://github.com/SKA-ScienceDataProcessor/integration-prototype/tree/master/sip/platform/logging
Author: SKA SDP SIP team.
License: UNKNOWN
Platform: UNKNOWN
Classifier: Programming Language :: Python :: 3 :: Only
Classifier: Development Status :: 1 - Planning
Classifier: License :: OSI Approved :: BSD License
